{"nodes": [{"id": "oros_doc_oros", "label": "OROS (Open Runtime Operating System)", "file_type": "document", "source_file": "OROS_Design_Document.md", "source_location": "1", "source_url": null, "captured_at": null, "author": null, "contributor": null}, {"id": "oros_doc_lythd", "label": "lythd (PID 1 supervisor)", "file_type": "document", "source_file": "OROS_Design_Document.md", "source_location": "29", "source_url": null, "captured_at": null, "author": null, "contributor": null}, {"id": "oros_doc_lythdist", "label": "lythdist (capability distributor)", "file_type": "document", "source_file": "OROS_Design_Document.md", "source_location": "30", "source_url": null, "captured_at": null, "author": null, "contributor": null}, {"id": "oros_doc_lythmsg", "label": "lythmsg (IPC bus)", "file_type": "document", "source_file": "OROS_Design_Document.md", "source_location": "31", "source_url": null, "captured_at": null, "author": null, "contributor": null}, {"id": "oros_doc_rpkg", "label": "rpkg (package manager)", "file_type": "document", "source_file": "OROS_Design_Document.md", "source_location": "82", "source_url": null, "captured_at": null, "author": null, "contributor": null}, {"id": "oros_doc_lysh", "label": "lysh (system shell)", "file_type": "document", "source_file": "OROS_Design_Document.md", "source_location": "87", "source_url": null, "captured_at": null, "author": null, "contributor": null}, {"id": "oros_doc_rpbreak", "label": "rpbreak (chaos engineering tool)", "file_type": "document", "source_file": "OROS_Design_Document.md", "source_location": "83", "source_url": null, "captured_at": null, "author": null, "contributor": null}, {"id": "oros_doc_rpview", "label": "rpview (service TUI)", "file_type": "document", "source_file": "OROS_Design_Document.md", "source_location": "84", "source_url": null, "captured_at": null, "author": null, "contributor": null}, {"id": "oros_doc_lythos_std", "label": "lythos-std (native runtime)", "file_type": "document", "source_file": "OROS_Design_Document.md", "source_location": "134", "source_url": null, "captured_at": null, "author": null, "contributor": null}, {"id": "oros_doc_linux_compat", "label": "lythos-linux-compat (Linux compat server)", "file_type": "document", "source_file": "OROS_Design_Document.md", "source_location": "145", "source_url": null, "captured_at": null, "author": null, "contributor": null}, {"id": "oros_doc_btrfs_layout", "label": "Btrfs Subvolume Layout (@core, @store, @cfg, @home)", "file_type": "document", "source_file": "OROS_Design_Document.md", "source_location": "56", "source_url": null, "captured_at": null, "author": null, "contributor": null}, {"id": "oros_doc_rollback_timer", "label": "30-second Stability/Rollback Timer", "file_type": "document", "source_file": "OROS_Design_Document.md", "source_location": "27", "source_url": null, "captured_at": null, "author": null, "contributor": null}, {"id": "oros_doc_boot_sequence", "label": "OROS Boot Sequence", "file_type": "document", "source_file": "OROS_Design_Document.md", "source_location": "36", "source_url": null, "captured_at": null, "author": null, "contributor": null}], "edges": [{"source": "oros_doc_oros", "target": "oros_doc_lythd", "relation": "references", "confidence": "EXTRACTED", "confidence_score": 1.0, "source_file": "OROS_Design_Document.md", "source_location": "29", "weight": 1.0}, {"source": "oros_doc_oros", "target": "oros_doc_lythdist", "relation": "references", "confidence": "EXTRACTED", "confidence_score": 1.0, "source_file": "OROS_Design_Document.md", "source_location": "30", "weight": 1.0}, {"source": "oros_doc_oros", "target": "oros_doc_lythmsg", "relation": "references", "confidence": "EXTRACTED", "confidence_score": 1.0, "source_file": "OROS_Design_Document.md", "source_location": "31", "weight": 1.0}, {"source": "oros_doc_oros", "target": "oros_doc_btrfs_layout", "relation": "references", "confidence": "EXTRACTED", "confidence_score": 1.0, "source_file": "OROS_Design_Document.md", "source_location": "56", "weight": 1.0}, {"source": "oros_doc_oros", "target": "oros_doc_rpkg", "relation": "references", "confidence": "EXTRACTED", "confidence_score": 1.0, "source_file": "OROS_Design_Document.md", "source_location": "82", "weight": 1.0}, {"source": "oros_doc_oros", "target": "oros_doc_lysh", "relation": "references", "confidence": "EXTRACTED", "confidence_score": 1.0, "source_file": "OROS_Design_Document.md", "source_location": "87", "weight": 1.0}, {"source": "oros_doc_oros", "target": "oros_doc_lythos_std", "relation": "references", "confidence": "EXTRACTED", "confidence_score": 1.0, "source_file": "OROS_Design_Document.md", "source_location": "134", "weight": 1.0}, {"source": "oros_doc_oros", "target": "oros_doc_linux_compat", "relation": "references", "confidence": "EXTRACTED", "confidence_score": 1.0, "source_file": "OROS_Design_Document.md", "source_location": "145", "weight": 1.0}, {"source": "oros_doc_lythd", "target": "oros_doc_rollback_timer", "relation": "references", "confidence": "EXTRACTED", "confidence_score": 1.0, "source_file": "OROS_Design_Document.md", "source_location": "29", "weight": 1.0}, {"source": "oros_doc_rpkg", "target": "oros_doc_rollback_timer", "relation": "references", "confidence": "EXTRACTED", "confidence_score": 1.0, "source_file": "OROS_Design_Document.md", "source_location": "113", "weight": 1.0}, {"source": "oros_doc_boot_sequence", "target": "oros_doc_lythd", "relation": "references", "confidence": "EXTRACTED", "confidence_score": 1.0, "source_file": "OROS_Design_Document.md", "source_location": "43", "weight": 1.0}, {"source": "oros_doc_boot_sequence", "target": "oros_doc_lythdist", "relation": "references", "confidence": "EXTRACTED", "confidence_score": 1.0, "source_file": "OROS_Design_Document.md", "source_location": "44", "weight": 1.0}, {"source": "oros_doc_boot_sequence", "target": "oros_doc_lythmsg", "relation": "references", "confidence": "EXTRACTED", "confidence_score": 1.0, "source_file": "OROS_Design_Document.md", "source_location": "46", "weight": 1.0}, {"source": "oros_doc_lythd", "target": "oros_doc_lythdist", "relation": "conceptually_related_to", "confidence": "EXTRACTED", "confidence_score": 1.0, "source_file": "OROS_Design_Document.md", "source_location": "43", "weight": 1.0}, {"source": "oros_doc_lythdist", "target": "oros_doc_lythmsg", "relation": "conceptually_related_to", "confidence": "EXTRACTED", "confidence_score": 1.0, "source_file": "OROS_Design_Document.md", "source_location": "46", "weight": 1.0}, {"source": "oros_doc_rollback_timer", "target": "oros_doc_btrfs_layout", "relation": "conceptually_related_to", "confidence": "EXTRACTED", "confidence_score": 1.0, "source_file": "OROS_Design_Document.md", "source_location": "164", "weight": 1.0}, {"source": "oros_doc_lythos_std", "target": "syscall_sys_numbers", "relation": "references", "confidence": "INFERRED", "confidence_score": 0.85, "source_file": "OROS_Design_Document.md", "source_location": "137", "weight": 1.0}, {"source": "oros_doc_rpkg", "target": "oros_doc_btrfs_layout", "relation": "conceptually_related_to", "confidence": "EXTRACTED", "confidence_score": 1.0, "source_file": "OROS_Design_Document.md", "source_location": "107", "weight": 1.0}, {"source": "oros_doc_rpbreak", "target": "oros_doc_rollback_timer", "relation": "conceptually_related_to", "confidence": "EXTRACTED", "confidence_score": 1.0, "source_file": "OROS_Design_Document.md", "source_location": "169", "weight": 1.0}, {"source": "oros_doc_rpview", "target": "oros_doc_lythmsg", "relation": "references", "confidence": "EXTRACTED", "confidence_score": 1.0, "source_file": "OROS_Design_Document.md", "source_location": "168", "weight": 1.0}], "hyperedges": [{"id": "oros_critical_triad", "label": "OROS Critical Daemon Triad (lythd + lythdist + lythmsg) triggers rollback", "nodes": ["oros_doc_lythd", "oros_doc_lythdist", "oros_doc_lythmsg", "oros_doc_rollback_timer"], "relation": "participate_in", "confidence": "EXTRACTED", "confidence_score": 1.0, "source_file": "OROS_Design_Document.md"}]}